{
    "app_name": "HexString",
    "version": "1.4.1",
    "rom_file": "Final Fantasy (USA).nes",
    "tbl_file": "Final Fantasy (USA).tbl",
    "script_file": "Final Fantasy (USA)_script.bin",
    "pointer_size": "2 bytes",
    "endianess": 0,
    "pointers_start_offset": "28010",
    "pointers_end_offset": "2820F",
    "pointers_base": "20010",
    "text_start_offset": "28210",
    "text_end_offset": "2B495",
    "end_line": "00",
    "fill_free_space_byte": "00",
    "no_use_comments_lines": false,
    "brackets": 0,
    "fill_free_space": true,
    "use_split_pointers": false,
    "not_use_end_line": false,
    "use_compression_method": false,
    "compression_algorithm": 0,
    "compression_variant": 0,
    "compare_to_dictionary": 0,
    "search_combinations": false,
    "max_frecuencies": "99",
    "max_char_lenght": "2"
}